README.md
setup.py
mosmqtt_oauth/__init__.py
mosmqtt_oauth/lib.py
mosmqtt_oauth/plugin.py
mosmqtt_oauth.egg-info/PKG-INFO
mosmqtt_oauth.egg-info/SOURCES.txt
mosmqtt_oauth.egg-info/dependency_links.txt
mosmqtt_oauth.egg-info/not-zip-safe
mosmqtt_oauth.egg-info/requires.txt
mosmqtt_oauth.egg-info/top_level.txt